Metadata-Version: 2.1
Name: django2-asyncmailer
Version: 0.0.4
Summary: Async email solution w/ multiple SMTP credentials, load-balancing and blacklist.
